[{"type": "Convolutional", "layerConfig": {"kernelInitializer": "varianceScaling", "activation": "relu", "kernelSize": 5, "strides": 1, "filters": 16, "inputShape": [28, 28, 1]}}, {"type": "Convolutional", "layerConfig": {"kernelInitializer": "varianceScaling", "strides": 1, "activation": "relu", "filters": 8, "kernelSize": 3}}, {"type": "maxPooling", "layerConfig": {"strides": [2, 2], "poolSize": [2, 2]}}, {"type": "Flatten", "layerConfig": {}}, {"type": "Dense", "layerConfig": {"units": 64, "activation": "relu"}}]